setup.py
timer_cm.py
timer_cm.egg-info/PKG-INFO
timer_cm.egg-info/SOURCES.txt
timer_cm.egg-info/dependency_links.txt
timer_cm.egg-info/top_level.txt